setup.py
ymci_ext_coverage/__init__.py
ymci_ext_coverage/db.py
ymci_ext_coverage/form.py
ymci_ext_coverage/hooks.py
ymci_ext_coverage/routes.py
ymci_ext_coverage.egg-info/PKG-INFO
ymci_ext_coverage.egg-info/SOURCES.txt
ymci_ext_coverage.egg-info/dependency_links.txt
ymci_ext_coverage.egg-info/entry_points.txt
ymci_ext_coverage.egg-info/top_level.txt
ymci_ext_coverage/templates/source.html