Metadata-Version: 1.1
Name: ymci-ext-coverage
Version: 1.4.0
Summary: Coverage (cobertura) plugin for ymci
Home-page: UNKNOWN
Author: Florian Mounier, Kozea
Author-email: florian.mounier@kozea.fr
License: UNKNOWN
Platform: Any
Provides: ymci_ext_coverage
